odoo/addons/account_e-invoice_generate/README.rst
odoo/addons/account_e-invoice_generate/__init__.py
odoo/addons/account_e-invoice_generate/__manifest__.py
odoo/addons/account_e-invoice_generate/i18n/account_e-invoice_generate.pot
odoo/addons/account_e-invoice_generate/i18n/fr.po
odoo/addons/account_e-invoice_generate/i18n/fr_FR.po
odoo/addons/account_e-invoice_generate/i18n/hr.po
odoo/addons/account_e-invoice_generate/i18n/nl.po
odoo/addons/account_e-invoice_generate/models/__init__.py
odoo/addons/account_e-invoice_generate/models/account_move.py
odoo/addons/account_e-invoice_generate/models/res_company.py
odoo/addons/account_e-invoice_generate/models/res_config_settings.py
odoo/addons/account_e-invoice_generate/readme/CONFIGURE.rst
odoo/addons/account_e-invoice_generate/readme/CONTRIBUTORS.rst
odoo/addons/account_e-invoice_generate/readme/DESCRIPTION.rst
odoo/addons/account_e-invoice_generate/static/description/icon.png
odoo/addons/account_e-invoice_generate/static/description/index.html
odoo/addons/account_e-invoice_generate/tests/__init__.py
odoo/addons/account_e-invoice_generate/tests/test_einvoice_generate.py
odoo/addons/account_e-invoice_generate/views/res_config_settings.xml
odoo13_addon_account_e_invoice_generate-13.0.1.0.1.dev19.dist-info/METADATA
odoo13_addon_account_e_invoice_generate-13.0.1.0.1.dev19.dist-info/WHEEL
odoo13_addon_account_e_invoice_generate-13.0.1.0.1.dev19.dist-info/top_level.txt
odoo13_addon_account_e_invoice_generate-13.0.1.0.1.dev19.dist-info/RECORD
