Metadata-Version: 2.1
Name: odoo13-addon-account_e-invoice_generate
Version: 13.0.1.0.1.dev19
Summary: Technical module to generate PDF invoices with embedded XML file
Home-page: https://github.com/OCA/edi
Author: Akretion,Onestein,Odoo Community Association (OCA)
Author-email: support@odoo-community.org
License: AGPL-3
Classifier: Programming Language :: Python
Classifier: Framework :: Odoo
Classifier: Framework :: Odoo :: 13.0
Classifier: License :: OSI Approved :: GNU Affero General Public License v3
Requires-Python: >=3.5
Requires-Dist: odoo<13.1dev,>=13.0a
